{
    "total": [
        {
            "id": "100067191000400",
            "count": 61
        },
        {
            "id": "100023576567175",
            "count": 366
        },
        {
            "id": "100047250972133",
            "count": 0
        },
        {
            "id": "100047128875560",
            "count": 1167
        },
        {
            "id": "100078366524561",
            "count": 16
        },
        {
            "id": "100090260659479",
            "count": 0
        },
        {
            "id": "61575204281961",
            "count": 18
        },
        {
            "id": "61576071635533",
            "count": 7
        },
        {
            "id": "61572245671963",
            "count": 0
        },
        {
            "id": "100094235645470",
            "count": 43
        },
        {
            "id": "61576707662544",
            "count": 265
        },
        {
            "id": "61576910752798",
            "count": 40
        },
        {
            "id": "61577095044815",
            "count": 0
        },
        {
            "id": "100094089697594",
            "count": 143
        },
        {
            "id": "61576889843853",
            "count": 0
        },
        {
            "id": "100000704902763",
            "count": 6
        }
    ],
    "week": [
        {
            "id": "100067191000400",
            "count": 61
        },
        {
            "id": "100023576567175",
            "count": 366
        },
        {
            "id": "100047250972133",
            "count": 0
        },
        {
            "id": "100047128875560",
            "count": 1167
        },
        {
            "id": "100078366524561",
            "count": 16
        },
        {
            "id": "100090260659479",
            "count": 0
        },
        {
            "id": "61575204281961",
            "count": 18
        },
        {
            "id": "61576071635533",
            "count": 7
        },
        {
            "id": "61572245671963",
            "count": 0
        },
        {
            "id": "100094235645470",
            "count": 43
        },
        {
            "id": "61576707662544",
            "count": 265
        },
        {
            "id": "61576910752798",
            "count": 40
        },
        {
            "id": "61577095044815",
            "count": 0
        },
        {
            "id": "100094089697594",
            "count": 143
        },
        {
            "id": "61576889843853",
            "count": 0
        },
        {
            "id": "100000704902763",
            "count": 6
        }
    ],
    "day": [
        {
            "id": "100067191000400",
            "count": 61
        },
        {
            "id": "100023576567175",
            "count": 366
        },
        {
            "id": "100047250972133",
            "count": 0
        },
        {
            "id": "100047128875560",
            "count": 1167
        },
        {
            "id": "100078366524561",
            "count": 16
        },
        {
            "id": "100090260659479",
            "count": 0
        },
        {
            "id": "61575204281961",
            "count": 18
        },
        {
            "id": "61576071635533",
            "count": 7
        },
        {
            "id": "61572245671963",
            "count": 0
        },
        {
            "id": "100094235645470",
            "count": 43
        },
        {
            "id": "61576707662544",
            "count": 265
        },
        {
            "id": "61576910752798",
            "count": 40
        },
        {
            "id": "61577095044815",
            "count": 0
        },
        {
            "id": "100094089697594",
            "count": 143
        },
        {
            "id": "61576889843853",
            "count": 0
        },
        {
            "id": "100000704902763",
            "count": 6
        }
    ],
    "time": 0,
    "last": {
        "time": 1,
        "day": [
            {
                "id": "100067191000400",
                "count": 0
            },
            {
                "id": "100023576567175",
                "count": 0
            },
            {
                "id": "100047250972133",
                "count": 0
            },
            {
                "id": "100047128875560",
                "count": 0
            },
            {
                "id": "100078366524561",
                "count": 0
            },
            {
                "id": "100000704902763",
                "count": 0
            },
            {
                "id": "100090260659479",
                "count": 0
            },
            {
                "id": "100093852656737",
                "count": 0
            },
            {
                "id": "61575204281961",
                "count": 0
            },
            {
                "id": "61576071635533",
                "count": 0
            },
            {
                "id": "61572245671963",
                "count": 0
            },
            {
                "id": "100094235645470",
                "count": 0
            },
            {
                "id": "61576707662544",
                "count": 0
            },
            {
                "id": "61568136634826",
                "count": 0
            },
            {
                "id": "61576910752798",
                "count": 0
            },
            {
                "id": "61577095044815",
                "count": 0
            },
            {
                "id": "100094089697594",
                "count": 0
            },
            {
                "id": "61576889843853",
                "count": 0
            }
        ],
        "week": [
            {
                "id": "100067191000400",
                "count": 0
            },
            {
                "id": "100023576567175",
                "count": 0
            },
            {
                "id": "100047250972133",
                "count": 0
            },
            {
                "id": "100047128875560",
                "count": 0
            },
            {
                "id": "100078366524561",
                "count": 0
            },
            {
                "id": "100000704902763",
                "count": 0
            },
            {
                "id": "100090260659479",
                "count": 0
            },
            {
                "id": "100093852656737",
                "count": 0
            },
            {
                "id": "61575204281961",
                "count": 0
            },
            {
                "id": "61576071635533",
                "count": 0
            },
            {
                "id": "61572245671963",
                "count": 0
            },
            {
                "id": "100094235645470",
                "count": 0
            },
            {
                "id": "61576707662544",
                "count": 0
            },
            {
                "id": "61568136634826",
                "count": 0
            },
            {
                "id": "61576910752798",
                "count": 0
            },
            {
                "id": "61577095044815",
                "count": 0
            },
            {
                "id": "100094089697594",
                "count": 0
            },
            {
                "id": "61576889843853",
                "count": 0
            }
        ]
    }
}