{
    "total": [
        {
            "id": "61559282801359",
            "count": 0
        },
        {
            "id": "61560407583530",
            "count": 0
        },
        {
            "id": "61560450915670",
            "count": 0
        },
        {
            "id": "100093051642489",
            "count": 64
        },
        {
            "id": "100039111428595",
            "count": 68
        }
    ],
    "week": [
        {
            "id": "61559282801359",
            "count": 0,
            "name": "Plinh Cutii"
        },
        {
            "id": "61560407583530",
            "count": 0,
            "name": "Người dùng facebook"
        },
        {
            "id": "61560450915670",
            "count": 0,
            "name": "ᏮᏮᏮ ᏮᏮᏮ"
        },
        {
            "id": "100093051642489",
            "count": 0,
            "name": "Đỗ Hải Phong"
        },
        {
            "id": "100039111428595",
            "count": 0,
            "name": "Người dùng facebook"
        }
    ],
    "day": [
        {
            "id": "61559282801359",
            "count": 0,
            "name": "Plinh Cutii"
        },
        {
            "id": "61560407583530",
            "count": 0,
            "name": "Người dùng Facebook"
        },
        {
            "id": "61560450915670",
            "count": 0,
            "name": "Người dùng Facebook"
        },
        {
            "id": "100093051642489",
            "count": 0,
            "name": "Đỗ Hải Phong ToT"
        },
        {
            "id": "100039111428595",
            "count": 0,
            "name": "Người dùng facebook"
        }
    ],
    "time": 6
}